[{"items":[{"id":"m2","name":"Margherita Pizza","price":"12.99","description":"A classic pizza with fresh mozzarella, tomatoes, and basil on a thin and crispy crust.","image":"images/margherita-pizza.jpg","quantity":3}],"customer":{"name":"Faizan Ahmad","email":"faizanahmad2582001@gmail.com","street":"Faqirabad","postal-code":"24420","city":"Charsadda"},"id":"400.0312163128328"},{"items":[{"id":"m2","name":"Margherita Pizza","price":"12.99","description":"A classic pizza with fresh mozzarella, tomatoes, and basil on a thin and crispy crust.","image":"images/margherita-pizza.jpg","quantity":3}],"customer":{"name":"Faizan Ahmad","email":"faizanahmad2582001@gmail.com","street":"Faqirabad","postal-code":"24420","city":"Charsadda"},"id":"851.5044797575773"},{"items":[{"id":"m2","name":"Margherita Pizza","price":"12.99","description":"A classic pizza with fresh mozzarella, tomatoes, and basil on a thin and crispy crust.","image":"images/margherita-pizza.jpg","quantity":4}],"customer":{"name":"Faizan Ahmad","email":"faizanahmad2582001@gmail.com","street":"Faqirabad","postal-code":"24420","city":"Charsadda"},"id":"528.8243558990687"},{"items":[{"id":"m2","name":"Margherita Pizza","price":"12.99","description":"A classic pizza with fresh mozzarella, tomatoes, and basil on a thin and crispy crust.","image":"images/margherita-pizza.jpg","quantity":4}],"customer":{"name":"Faizan Ahmad","email":"faizanahmad2582001@gmail.com","street":"Faqirabad","postal-code":"24420","city":"Charsadda"},"id":"4.7363488328300285"},{"items":[{"id":"m2","name":"Margherita Pizza","price":"12.99","description":"A classic pizza with fresh mozzarella, tomatoes, and basil on a thin and crispy crust.","image":"images/margherita-pizza.jpg","quantity":4}],"customer":{"name":"Faizan Ahmad","email":"faizanahmad2582001@gmail.com","street":"Faqirabad","postal-code":"24420","city":"Charsadda"},"id":"665.637752128658"},{"items":[{"id":"m2","name":"Margherita Pizza","price":"12.99","description":"A classic pizza with fresh mozzarella, tomatoes, and basil on a thin and crispy crust.","image":"images/margherita-pizza.jpg","quantity":4}],"customer":{"name":"Faizan Ahmad","email":"faizanahmad2582001@gmail.com","street":"Faqirabad","postal-code":"24420","city":"Charsadda"},"id":"239.667127861795"},{"items":[{"id":"m2","name":"Margherita Pizza","price":"12.99","description":"A classic pizza with fresh mozzarella, tomatoes, and basil on a thin and crispy crust.","image":"images/margherita-pizza.jpg","quantity":4}],"customer":{"name":"Faizan Ahmad","email":"faizanahmad2582001@gmail.com","street":"Faqirabad","postal-code":"24420","city":"Charsadda"},"id":"575.9664794007826"},{"items":[{"id":"m2","name":"Margherita Pizza","price":"12.99","description":"A classic pizza with fresh mozzarella, tomatoes, and basil on a thin and crispy crust.","image":"images/margherita-pizza.jpg","quantity":4}],"customer":{"name":"Faizan Ahmad","email":"faizanahmad2582001@gmail.com","street":"Faqirabad","postal-code":"24420","city":"Charsadda"},"id":"862.9212913809208"},{"items":[{"id":"m2","name":"Margherita Pizza","price":"12.99","description":"A classic pizza with fresh mozzarella, tomatoes, and basil on a thin and crispy crust.","image":"images/margherita-pizza.jpg","quantity":4}],"customer":{"name":"Faizan Ahmad","email":"faizanahmad2582001@gmail.com","street":"Faqirabad","postal-code":"24420","city":"Charsadda"},"id":"675.7510767288353"},{"items":[{"id":"m2","name":"Margherita Pizza","price":"12.99","description":"A classic pizza with fresh mozzarella, tomatoes, and basil on a thin and crispy crust.","image":"images/margherita-pizza.jpg","quantity":4}],"customer":{"name":"Faizan Ahmad","email":"faizanahmad2582001@gmail.com","street":"Faqirabad","postal-code":"24420","city":"Charsadda"},"id":"837.7067625508963"},{"items":[{"id":"m2","name":"Margherita Pizza","price":"12.99","description":"A classic pizza with fresh mozzarella, tomatoes, and basil on a thin and crispy crust.","image":"images/margherita-pizza.jpg","quantity":4}],"customer":{"name":"Faizan Ahmad","email":"faizanahmad2582001@gmail.com","street":"Faqirabad","postal-code":"24420","city":"Charsadda"},"id":"822.4094696427546"},{"items":[{"id":"m2","name":"Margherita Pizza","price":"12.99","description":"A classic pizza with fresh mozzarella, tomatoes, and basil on a thin and crispy crust.","image":"images/margherita-pizza.jpg","quantity":4}],"customer":{"name":"Faizan Ahmad","email":"faizanahmad2582001@gmail.com","street":"Faqirabad","postal-code":"24420","city":"Charsadda"},"id":"178.98394594425326"},{"items":[{"id":"m2","name":"Margherita Pizza","price":"12.99","description":"A classic pizza with fresh mozzarella, tomatoes, and basil on a thin and crispy crust.","image":"images/margherita-pizza.jpg","quantity":4}],"customer":{"name":"Faizan Ahmad","email":"faizanahmad2582001@gmail.com","street":"Faqirabad","postal-code":"24420","city":"Charsadda"},"id":"84.99514060312264"},{"items":[{"id":"m2","name":"Margherita Pizza","price":"12.99","description":"A classic pizza with fresh mozzarella, tomatoes, and basil on a thin and crispy crust.","image":"images/margherita-pizza.jpg","quantity":4}],"customer":{"name":"Faizan Ahmad","email":"faizanahmad2582001@gmail.com","street":"Faqirabad","postal-code":"24420","city":"Charsadda"},"id":"894.8261574852708"},{"items":[{"id":"m2","name":"Margherita Pizza","price":"12.99","description":"A classic pizza with fresh mozzarella, tomatoes, and basil on a thin and crispy crust.","image":"images/margherita-pizza.jpg","quantity":4}],"customer":{"name":"Faizan Ahmad","email":"faizanahmad2582001@gmail.com","street":"Faqirabad","postal-code":"24420","city":"Charsadda"},"id":"670.5350109718362"},{"items":[{"id":"m2","name":"Margherita Pizza","price":"12.99","description":"A classic pizza with fresh mozzarella, tomatoes, and basil on a thin and crispy crust.","image":"images/margherita-pizza.jpg","quantity":4}],"customer":{"name":"Faizan Ahmad","email":"faizanahmad2582001@gmail.com","street":"Faqirabad","postal-code":"24420","city":"Charsadda"},"id":"697.2608551240392"},{"items":[{"id":"m2","name":"Margherita Pizza","price":"12.99","description":"A classic pizza with fresh mozzarella, tomatoes, and basil on a thin and crispy crust.","image":"images/margherita-pizza.jpg","quantity":4}],"customer":{"name":"Faizan Ahmad","email":"faizanahmad2582001@gmail.com","street":"Faqirabad","postal-code":"24420","city":"Charsadda"},"id":"637.0024358713733"},{"items":[{"id":"m2","name":"Margherita Pizza","price":"12.99","description":"A classic pizza with fresh mozzarella, tomatoes, and basil on a thin and crispy crust.","image":"images/margherita-pizza.jpg","quantity":1}],"customer":{"name":"Faizan Ahmad","email":"faizanahmad2582001@gmail.com","street":"Faqirabad","postal-code":"24420","city":"Charsadda"},"id":"606.426780264833"},{"items":[{"id":"m2","name":"Margherita Pizza","price":"12.99","description":"A classic pizza with fresh mozzarella, tomatoes, and basil on a thin and crispy crust.","image":"images/margherita-pizza.jpg","quantity":1}],"customer":{"name":"Faizan Ahmad","email":"faizanahmad2582001@gmail.com","street":"Faqirabad","postal-code":"24420","city":"Charsadda"},"id":"266.6652781925809"},{"items":[{"id":"m2","name":"Margherita Pizza","price":"12.99","description":"A classic pizza with fresh mozzarella, tomatoes, and basil on a thin and crispy crust.","image":"images/margherita-pizza.jpg","quantity":1}],"customer":{"name":"Faizan Ahmad","email":"faizanahmad2582001@gmail.com","street":"Faqirabad","postal-code":"24420","city":"Charsadda"},"id":"888.4740155363191"},{"items":[{"id":"m2","name":"Margherita Pizza","price":"12.99","description":"A classic pizza with fresh mozzarella, tomatoes, and basil on a thin and crispy crust.","image":"images/margherita-pizza.jpg","quantity":4}],"customer":{"name":"Faizan Ahmad","email":"faizanahmad2582001@gmail.com","street":"Faqirabad","postal-code":"24420","city":"Charsadda"},"id":"552.3177582431731"},{"items":[{"id":"m2","name":"Margherita Pizza","price":"12.99","description":"A classic pizza with fresh mozzarella, tomatoes, and basil on a thin and crispy crust.","image":"images/margherita-pizza.jpg","quantity":3}],"customer":{"name":"Faizan Ahmad","email":"faizanahmad2582001@gmail.com","street":"Faqirabad","postal-code":"24420","city":"Charsadda"},"id":"920.7437660703592"},{"items":[{"id":"m2","name":"Margherita Pizza","price":"12.99","description":"A classic pizza with fresh mozzarella, tomatoes, and basil on a thin and crispy crust.","image":"images/margherita-pizza.jpg","quantity":3}],"customer":{"name":"Faizan Ahmad","email":"faizanahmad2582001@gmail.com","street":"Faqirabad","postal-code":"24420","city":"Charsadda"},"id":"720.8281598749244"},{"items":[{"id":"m2","name":"Margherita Pizza","price":"12.99","description":"A classic pizza with fresh mozzarella, tomatoes, and basil on a thin and crispy crust.","image":"images/margherita-pizza.jpg","quantity":1}],"customer":{"name":"Faizan Ahmad","email":"faizanahmad2582001@gmail.com","street":"Faqirabad","postal-code":"24420","city":"Charsadda"},"id":"947.4753894327979"},{"items":[{"id":"m2","name":"Margherita Pizza","price":"12.99","description":"A classic pizza with fresh mozzarella, tomatoes, and basil on a thin and crispy crust.","image":"images/margherita-pizza.jpg","quantity":4}],"customer":{"name":"Faizan Ahmad","email":"faizanahmad2582001@gmail.com","street":"Faqirabad","postal-code":"24420","city":"Charsadda"},"id":"565.7918280086309"}]